pimpy_c.cp36-win32.pyd
pimpy/__init__.py
pimpy/color_cluster.py
pimpy/smoothing.py
pimpy/transformations.py
pimpy-0.1.0.dist-info/LICENSE.txt
pimpy-0.1.0.dist-info/METADATA
pimpy-0.1.0.dist-info/WHEEL
pimpy-0.1.0.dist-info/top_level.txt
pimpy-0.1.0.dist-info/RECORD
