Metadata-Version: 2.1
Name: pimpy
Version: 0.1.0
Summary: Contains selected image processing functions
Home-page: https://gitlab.com/pschill/pimpy
Author: Philip Schill
Author-email: philip.schill@gmx.de
License: UNKNOWN
Platform: UNKNOWN
Classifier: Programming Language :: Python :: 3.6
Classifier: Programming Language :: Python :: 3.7
Classifier: License :: OSI Approved :: MIT License
Classifier: Operating System :: OS Independent
Requires-Python: >=3.6
Requires-Dist: numpy (>=1.15)
Requires-Dist: scipy (>=1.1)
